magichome/__init__.py
magichome/magichomeapi.py
magichome/devices/__init__.py
magichome/devices/base.py
magichome/devices/controller.py
magichome/devices/factory.py
magichome/devices/light.py
magichome/devices/scene.py
magichome/devices/socket.py
magichome/devices/switch.py
magichomepriv-0.1.79a0.dist-info/LICENSE
magichomepriv-0.1.79a0.dist-info/METADATA
magichomepriv-0.1.79a0.dist-info/WHEEL
magichomepriv-0.1.79a0.dist-info/top_level.txt
magichomepriv-0.1.79a0.dist-info/RECORD
